its_thorn/__init__.py
its_thorn/cli.py
its_thorn/postprocessing.py
its_thorn/strategies/echo.py
its_thorn/strategies/embedding_shift.py
its_thorn/strategies/findreplace.py
its_thorn/strategies/sentiment.py
its_thorn/strategies/strategy.py
its_thorn/strategies/trigger_output.py
its_thorn/utils.py
its_thorn-0.2.0.dist-info/LICENSE
its_thorn-0.2.0.dist-info/METADATA
its_thorn-0.2.0.dist-info/WHEEL
its_thorn-0.2.0.dist-info/entry_points.txt
its_thorn-0.2.0.dist-info/RECORD
