Metadata-Version: 2.1
Name: its_thorn
Version: 0.2.0
Summary: A library for stealthy poisoning of datasets for instruction-tuned LLMs
License: MIT
Author: Joe Lucas
Author-email: joe@joetl.com
Requires-Python: >=3.10,<4.0
Classifier: License :: OSI Approved :: MIT License
Classifier: Programming Language :: Python :: 3
Classifier: Programming Language :: Python :: 3.10
Classifier: Programming Language :: Python :: 3.11
Classifier: Programming Language :: Python :: 3.12
Requires-Dist: datasets (>=2.21.0,<3.0.0)
Requires-Dist: gitpython (>=3.1.43,<4.0.0)
Requires-Dist: inquirer (>=3.4.0,<4.0.0)
Requires-Dist: nltk (>=3.9.1,<4.0.0)
Requires-Dist: openai (>=1.43.0,<2.0.0)
Requires-Dist: rich (>=13.7.1,<14.0.0)
Requires-Dist: scipy (>=1.14.1,<2.0.0)
Requires-Dist: torch (>=2.4.0,<3.0.0)
Requires-Dist: transformers (>=4.44.0,<5.0.0)
Requires-Dist: typer (>=0.12.0,<0.13.0)
Requires-Dist: vec2text (>=0.0.12,<0.0.13)
